libinsdb/__init__.py
libinsdb/__main__.py
libinsdb/__main__.py~
libinsdb/instrumentdb.py
libinsdb/local.py
libinsdb/objects.py
libinsdb/remote.py
libinsdb-0.9.0.dist-info/METADATA
libinsdb-0.9.0.dist-info/WHEEL
libinsdb-0.9.0.dist-info/entry_points.txt
libinsdb-0.9.0.dist-info/licenses/LICENSE.md
libinsdb-0.9.0.dist-info/RECORD
