Metadata-Version: 2.4
Name: libinsdb
Version: 0.9.0
Summary: Library to access InstrumentDB databases
Author-email: Maurizio Tomasi <maurizio.tomasi@unimi.it>
License-Expression: MIT
License-File: LICENSE.md
Requires-Python: <4,>=3.10
Requires-Dist: coverage<8,>=7.3.0
Requires-Dist: python-dateutil<3,>=2.8.2
Requires-Dist: pyyaml<7,>=6.0.1
Requires-Dist: requests-mock<2,>=1.11.0
Requires-Dist: requests<3,>=2.31.0
Requires-Dist: rich>=14.0
Requires-Dist: tomlkit<0.13,>=0.12.1
Requires-Dist: types-pyyaml<7,>=6.0.12.12
Provides-Extra: docs
Requires-Dist: sphinx>=7.1.2; extra == 'docs'
